validate_field/__init__.py
validate_field/validation.py
validate_field-2.0.1.dist-info/LICENSE
validate_field-2.0.1.dist-info/METADATA
validate_field-2.0.1.dist-info/WHEEL
validate_field-2.0.1.dist-info/top_level.txt
validate_field-2.0.1.dist-info/RECORD
